_qdp/__init__.py
_qdp/_qdp.cpython-310-x86_64-linux-gnu.so
_qdp.libs/libcudart-b5a066d7.so.12
qumat_qdp-0.1.0rc2.dist-info/METADATA
qumat_qdp-0.1.0rc2.dist-info/WHEEL
qumat_qdp-0.1.0rc2.dist-info/RECORD
