Metadata-Version: 2.4
Name: qumat-qdp
Version: 0.1.0rc2
Classifier: Programming Language :: Rust
Classifier: Programming Language :: Python :: Implementation :: CPython
Classifier: Programming Language :: Python :: Implementation :: PyPy
Requires-Dist: qumat>0.4.0
Requires-Python: >=3.10, <3.13
